seoul/__init__.py
seoul/client.py
seoul/air/__init__.py
seoul/subway/__init__.py
seoul/subway/constants.py
seoul/subway/train.py
seoul-0.2.0.dist-info/LICENSE
seoul-0.2.0.dist-info/METADATA
seoul-0.2.0.dist-info/WHEEL
seoul-0.2.0.dist-info/top_level.txt
seoul-0.2.0.dist-info/RECORD
