Metadata-Version: 2.1
Name: seoul
Version: 0.2.0
Summary: Seoul public data API client library.
Home-page: https://github.com/limeburst/seoul-py
Author: Seo Jihyeok
Author-email: limeburst@icloud.com
License: UNKNOWN
Platform: UNKNOWN
Classifier: Programming Language :: Python :: 3
Classifier: License :: OSI Approved :: MIT License
Requires-Dist: requests
